distlock_client
