Metadata-Version: 1.1
Name: distlock-client
Version: 0.1.1
Summary: Distribute lock system's client.
Home-page: https://github.com/appstore-zencore/distlock-client
Author: zencore
Author-email: appstore@zencore.cn
License: MIT
Keywords: distlock-client,distlock
Platform: UNKNOWN
Classifier: Development Status :: 5 - Production/Stable
Classifier: Intended Audience :: Developers
Classifier: Topic :: Software Development :: Libraries :: Python Modules
Classifier: License :: OSI Approved :: MIT License
Classifier: Programming Language :: Python :: 3
Classifier: Programming Language :: Python :: 3 :: Only
Requires: requests
